{
"node_id": 0,
"node_name": "is_zero",
"constraints": ["(assert (and (= v_2 (ite (= 2 v_0) 1 0)) (= v_3 (ite (= 3 v_0) 1 0)) (= v_4 (ite (and (= v_2 0) (= v_3 0)) 0 1)) (or (= v_4 0) (= v_4 1)) (= v_5 (ite (= 5 v_0) 1 0)) (= v_6 (ite (and (= v_4 0) (= v_5 0)) 0 1)) (or (= v_6 0) (= v_6 1)) (= v_7 (ite (= 2 v_1) 1 0)) (= v_8 (ite (= 3 v_1) 1 0)) (= v_9 (ite (and (= v_7 0) (= v_8 0)) 0 1)) (or (= v_9 0) (= v_10 1)) (= v_10 (ite (= 5 v_1) 1 0)) (= v_11 (ite (and (= v_9 0) (= v_10 0)) 0 1)) (or (= v_11 0) (= v_11 1)) (= v_12 (ite (= v_1 v_0) 1 0)) (ite (= v_12 1) (= v_28 0) (and (= v_13 (ite (= 2 v_0) 1 0)) (= v_14 (ite (= 5 v_1) 1 0)) (= v_15 (ite (or (= v_13 0) (= v_14 0)) 0 1)) (or (= v_15 0) (= v_15 1)) (ite (= v_15 1) (and (= v_26 1) (= v_27 1)) (and (= v_16 (ite (= 3 v_0) 1 0)) (= v_17 (ite (= 2 v_1) 1 0)) (= v_18 (ite (or (= v_16 0) (= v_17 0)) 0 1)) (or (= v_18 0) (= v_18 1)) (ite (= v_18 1) (and (= v_24 1) (= v_25 1)) (and (= v_19 (ite (= 5 v_0) 1 0)) (= v_20 (ite (= 3 v_1) 1 0)) (= v_21 (ite (or (= v_19 0) (= v_20 0)) 0 1)) (or (= v_21 0) (= v_21 1)) (ite (= v_21 1) (and (= v_22 1) (= v_23 1)) (and (= v_22 2) (= v_23 2))) (= v_24 v_22) (= v_25 v_23))) (= v_26 v_24) (= v_27 v_25))) (= v_28 v_27))) (= v_29 v_28)))"],
  "input_signals": ["v_0", "v_1"],
  "output_signals": ["v_29"],
"signals": ["v_0", "v_1", "v_2", "v_3", "v_4", "v_5", "v_6", "v_7", "v_8", "v_9", "v_10", "v_11", "v_12", "v_13", "v_14", "v_15", "v_16", "v_17", "v_18", "v_19", "v_20", "v_21", "v_22", "v_23", "v_24", "v_25", "v_26", "v_27", "v_28", "v_29", "v_30"]}

